kivy4/__init__.py
Kivy4-5.3.1.dist-info/LICENSE.txt
Kivy4-5.3.1.dist-info/METADATA
Kivy4-5.3.1.dist-info/WHEEL
Kivy4-5.3.1.dist-info/top_level.txt
Kivy4-5.3.1.dist-info/RECORD
