Metadata-Version: 2.1
Name: Kivy4
Version: 5.3.1
Summary: This package allows you to create Kivy projects faster with a pre-made kivy template.
Author: Eshqol Development
Author-email: support@eshqol.com
License: MIT
Requires-Python: >=3.7
License-File: LICENSE.txt
Requires-Dist: kivy
Requires-Dist: kivymd
Requires-Dist: darkdetect
Requires-Dist: screeninfo
Requires-Dist: pyperclip
